{"version": 0.6, "generator": "Overpass API 0.7.62.8 e802775f", "osm3s": {"timestamp_osm_base": "2025-12-01T16:41:15Z", "copyright": "The data included in this document is from www.openstreetmap.org. The data is made available under ODbL."}, "elements": [{"type": "node", "id": 357616341, "lat": 40.8347222, "lon": -73.9413889, "tags": {"amenity": "school", "ele": "47", "gnis:feature_id": "2079019", "name": "Public School 4"}}, {"type": "node", "id": 357621183, "lat": 40.8333333, "lon": -73.9461111, "tags": {"addr:city": "New York", "addr:housenumber": "3755", "addr:postcode": "10032", "addr:street": "Broadway", "amenity": "college", "ele": "35", "gnis:feature_id": "2083783", "name": "Boricua College", "phone": "+1 212 694-1000", "website": "https://www.boricuacollege.edu/", "wikidata": "Q2910878", "wikipedia": "en:Boricua College"}}, {"type": "node", "id": 2796691184, "lat": 40.831546, "lon": -73.9424038, "tags": {"addr:housenumber": "475", "addr:postcode": "10032", "addr:street": "West 155th Street", "amenity": "school", "ele": "46", "gnis:feature_id": "961608", "name": "Public School 28"}}, {"type": "node", "id": 3627346235, "lat": 40.8344857, "lon": -73.9451934, "tags": {"addr:city": "New York", "addr:housenumber": "5", "addr:postcode": "10032", "addr:state": "NY", "addr:street": "Edward M. Morgan Place", "amenity": "restaurant", "cuisine": "spanish", "internet_access": "yes", "name": "Chez Messy"}}, {"type": "node", "id": 3627346237, "lat": 40.8334187, "lon": -73.9450216, "tags": {"amenity": "restaurant", "cuisine": "salvadoran;italian", "name": "La Libertad"}}, {"type": "node", "id": 3627374568, "lat": 40.8345935, "lon": -73.9452247, "tags": {"addr:city": "New York", "addr:housenumber": "9", "addr:postcode": "10032", "addr:state": "NY", "addr:street": "Edward M. Morgan Place", "amenity": "cafe", "check_date": "2025-07-27", "cuisine": "coffee_shop", "internet_access": "yes", "name": "Semicolon", "outdoor_seating": "yes", "payment:american_express": "yes", "payment:discover_card": "yes", "payment:mastercard": "yes", "payment:visa": "yes", "toilets": "yes"}}, {"type": "node", "id": 3627501381, "lat": 40.8340939, "lon": -73.9452869}, {"type": "node", "id": 3627534297, "lat": 40.8348921, "lon": -73.9446221, "tags": {"addr:city": "New York", "addr:housenumber": "3801", "addr:postcode": "10032", "addr:state": "NY", "addr:street": "Broadway", "amenity": "restaurant", "cuisine": "diner", "name": "Coral Diner"}}, {"type": "node", "id": 4701483771, "lat": 40.8407233, "lon": -73.9448951}, {"type": "node", "id": 4763738145, "lat": 40.83403, "lon": -73.9451373}, {"type": "node", "id": 4763738146, "lat": 40.8338617, "lon": -73.9452575}, {"type": "node", "id": 7127352914, "lat": 40.835561, "lon": -73.9455649}, {"type": "node", "id": 7127352915, "lat": 40.8352261, "lon": -73.9454767}, {"type": "node", "id": 7127352916, "lat": 40.8377738, "lon": -73.9470717}, {"type": "node", "id": 7127352917, "lat": 40.8384574, "lon": -73.946101}, {"type": "node", "id": 7127352918, "lat": 40.839142, "lon": -73.9461583}, {"type": "node", "id": 7127352919, "lat": 40.8368187, "lon": -73.9467833}, {"type": "node", "id": 7127352920, "lat": 40.8396761, "lon": -73.9456784}, {"type": "node", "id": 7127352922, "lat": 40.8366693, "lon": -73.9468965}, {"type": "node", "id": 7127352923, "lat": 40.8361574, "lon": -73.9464772}, {"type": "node", "id": 7127352924, "lat": 40.8358356, "lon": -73.9459828}, {"type": "node", "id": 7127352925, "lat": 40.8354329, "lon": -73.9456349}, {"type": "node", "id": 7127352926, "lat": 40.8376556, "lon": -73.9469236}, {"type": "node", "id": 7127352927, "lat": 40.838135, "lon": -73.9466471}, {"type": "node", "id": 7127352928, "lat": 40.8374881, "lon": -73.9470846}, {"type": "node", "id": 7127352929, "lat": 40.8380741, "lon": -73.9469223}, {"type": "node", "id": 7127352930, "lat": 40.8387136, "lon": -73.9457936}, {"type": "node", "id": 7127352931, "lat": 40.8389982, "lon": -73.9456408}, {"type": "node", "id": 7127352932, "lat": 40.8393034, "lon": -73.9456134}, {"type": "node", "id": 7127352933, "lat": 40.8397054, "lon": -73.945675}, {"type": "node", "id": 7127352934, "lat": 40.8405717, "lon": -73.9449582}, {"type": "node", "id": 7127352935, "lat": 40.8407394, "lon": -73.9448741}, {"type": "node", "id": 7127352936, "lat": 40.8392506, "lon": -73.9461127}, {"type": "node", "id": 7127352937, "lat": 40.8395234, "lon": -73.9459839}, {"type": "node", "id": 7127352938, "lat": 40.8365338, "lon": -73.9466252}, {"type": "node", "id": 7127352939, "lat": 40.8360238, "lon": -73.9460051}, {"type": "node", "id": 7127352940, "lat": 40.8355082, "lon": -73.9455387}, {"type": "node", "id": 7127352941, "lat": 40.8352241, "lon": -73.9454861}, {"type": "node", "id": 7127352942, "lat": 40.8381839, "lon": -73.9468367}, {"type": "node", "id": 7127352943, "lat": 40.8390578, "lon": -73.9462045}, {"type": "node", "id": 7127352944, "lat": 40.8391571, "lon": -73.946151}, {"type": "node", "id": 7127352945, "lat": 40.836426, "lon": -73.9465362}, {"type": "node", "id": 7127352946, "lat": 40.8398022, "lon": -73.9456541}, {"type": "node", "id": 7127352948, "lat": 40.8366284, "lon": -73.9468745}, {"type": "node", "id": 7127352949, "lat": 40.8361242, "lon": -73.9464364}, {"type": "node", "id": 7127352950, "lat": 40.8358012, "lon": -73.9459346}, {"type": "node", "id": 7127352951, "lat": 40.8353958, "lon": -73.9456149}, {"type": "node", "id": 7127352952, "lat": 40.8376993, "lon": -73.9469149}, {"type": "node", "id": 7127352953, "lat": 40.83817, "lon": -73.9466054}, {"type": "node", "id": 7127352954, "lat": 40.8375564, "lon": -73.947094}, {"type": "node", "id": 7127352955, "lat": 40.8381324, "lon": -73.946876}, {"type": "node", "id": 7127352956, "lat": 40.8390931, "lon": -73.946184}, {"type": "node", "id": 7127352957, "lat": 40.8387385, "lon": -73.9457736}, {"type": "node", "id": 7127352958, "lat": 40.8390206, "lon": -73.945635}, {"type": "node", "id": 7127352959, "lat": 40.8393317, "lon": -73.9456177}, {"type": "node", "id": 7127352960, "lat": 40.8397347, "lon": -73.9456699}, {"type": "node", "id": 7127352961, "lat": 40.8407074, "lon": -73.9448212}, {"type": "node", "id": 7127352962, "lat": 40.8407366, "lon": -73.9448803}, {"type": "node", "id": 7127352963, "lat": 40.8399645, "lon": -73.9455679}, {"type": "node", "id": 7127352964, "lat": 40.8394163, "lon": -73.9460357}, {"type": "node", "id": 7127352965, "lat": 40.8364637, "lon": -73.9465696}, {"type": "node", "id": 7127352966, "lat": 40.8359868, "lon": -73.9459492}, {"type": "node", "id": 7127352967, "lat": 40.8352487, "lon": -73.9454539}, {"type": "node", "id": 7127352968, "lat": 40.8352238, "lon": -73.9454942}, {"type": "node", "id": 7127352969, "lat": 40.8388201, "lon": -73.9463449}, {"type": "node", "id": 7127352970, "lat": 40.8390314, "lon": -73.9462176}, {"type": "node", "id": 7127352971, "lat": 40.8391742, "lon": -73.9461442}, {"type": "node", "id": 7127352972, "lat": 40.8361805, "lon": -73.9462533}, {"type": "node", "id": 7127352973, "lat": 40.8401581, "lon": -73.9453821}, {"type": "node", "id": 7127352974, "lat": 40.8365869, "lon": -73.9468526}, {"type": "node", "id": 7127352975, "lat": 40.8360921, "lon": -73.9463925}, {"type": "node", "id": 7127352976, "lat": 40.8357649, "lon": -73.9458905}, {"type": "node", "id": 7127352977, "lat": 40.8353197, "lon": -73.9455724}, {"type": "node", "id": 7127352978, "lat": 40.837736, "lon": -73.9469065}, {"type": "node", "id": 7127352979, "lat": 40.8381961, "lon": -73.9465682}, {"type": "node", "id": 7127352980, "lat": 40.8375975, "lon": -73.947098}, {"type": "node", "id": 7127352981, "lat": 40.8382321, "lon": -73.9467984}, {"type": "node", "id": 7127352982, "lat": 40.8384835, "lon": -73.9460592}, {"type": "node", "id": 7127352983, "lat": 40.838762, "lon": -73.945757}, {"type": "node", "id": 7127352984, "lat": 40.8390548, "lon": -73.9456273}, {"type": "node", "id": 7127352985, "lat": 40.8393704, "lon": -73.9456259}, {"type": "node", "id": 7127352986, "lat": 40.8397747, "lon": -73.9456617}, {"type": "node", "id": 7127352987, "lat": 40.8407165, "lon": -73.9448165}, {"type": "node", "id": 7127352988, "lat": 40.8407318, "lon": -73.944887}, {"type": "node", "id": 7127352989, "lat": 40.8400077, "lon": -73.9455308}, {"type": "node", "id": 7127352990, "lat": 40.8392888, "lon": -73.9460954}, {"type": "node", "id": 7127352991, "lat": 40.8363783, "lon": -73.9464876}, {"type": "node", "id": 7127352992, "lat": 40.8359379, "lon": -73.9458802}, {"type": "node", "id": 7127352993, "lat": 40.835255, "lon": -73.945454}, {"type": "node", "id": 7127352994, "lat": 40.8352248, "lon": -73.9455036}, {"type": "node", "id": 7127352995, "lat": 40.8388757, "lon": -73.9463091}, {"type": "node", "id": 7127352996, "lat": 40.8385797, "lon": -73.9459209}, {"type": "node", "id": 7127352997, "lat": 40.8395868, "lon": -73.9459494}, {"type": "node", "id": 7127352998, "lat": 40.8358236, "lon": -73.9457558}, {"type": "node", "id": 7127352999, "lat": 40.8407123, "lon": -73.9448173}, {"type": "node", "id": 7127353000, "lat": 40.8364871, "lon": -73.9467906}, {"type": "node", "id": 7127353001, "lat": 40.8360695, "lon": -73.9463595}, {"type": "node", "id": 7127353002, "lat": 40.8357333, "lon": -73.9458559}, {"type": "node", "id": 7127353003, "lat": 40.8371432, "lon": -73.9468565}, {"type": "node", "id": 7127353004, "lat": 40.8378229, "lon": -73.9468777}, {"type": "node", "id": 7127353005, "lat": 40.8382305, "lon": -73.9465127}, {"type": "node", "id": 7127353006, "lat": 40.8376617, "lon": -73.9470948}, {"type": "node", "id": 7127353007, "lat": 40.8383076, "lon": -73.946738}, {"type": "node", "id": 7127353008, "lat": 40.8387862, "lon": -73.9457403}, {"type": "node", "id": 7127353009, "lat": 40.8390862, "lon": -73.9456216}, {"type": "node", "id": 7127353010, "lat": 40.8394081, "lon": -73.9456347}, {"type": "node", "id": 7127353011, "lat": 40.8398673, "lon": -73.9456281}, {"type": "node", "id": 7127353012, "lat": 40.840722, "lon": -73.9448188}, {"type": "node", "id": 7127353013, "lat": 40.8406326, "lon": -73.9449873}, {"type": "node", "id": 7127353014, "lat": 40.8400706, "lon": -73.9454695}, {"type": "node", "id": 7127353015, "lat": 40.8391912, "lon": -73.9461372}, {"type": "node", "id": 7127353016, "lat": 40.8363403, "lon": -73.9464474}, {"type": "node", "id": 7127353017, "lat": 40.8358992, "lon": -73.9458311}, {"type": "node", "id": 7127353018, "lat": 40.8352643, "lon": -73.9454568}, {"type": "node", "id": 7127353019, "lat": 40.8352262, "lon": -73.9455149}, {"type": "node", "id": 7127353020, "lat": 40.8383853, "lon": -73.9462342}, {"type": "node", "id": 7127353021, "lat": 40.8385672, "lon": -73.9459349}, {"type": "node", "id": 7127353022, "lat": 40.8399007, "lon": -73.9457182}, {"type": "node", "id": 7127353023, "lat": 40.8354312, "lon": -73.9455064}, {"type": "node", "id": 7127353025, "lat": 40.8364437, "lon": -73.9467598}, {"type": "node", "id": 7127353026, "lat": 40.8360278, "lon": -73.9462949}, {"type": "node", "id": 7127353027, "lat": 40.835706, "lon": -73.9458238}, {"type": "node", "id": 7127353028, "lat": 40.8373786, "lon": -73.9468906}, {"type": "node", "id": 7127353029, "lat": 40.837872, "lon": -73.9468567}, {"type": "node", "id": 7127353030, "lat": 40.8382673, "lon": -73.9464578}, {"type": "node", "id": 7127353031, "lat": 40.8377145, "lon": -73.947087}, {"type": "node", "id": 7127353032, "lat": 40.8383836, "lon": -73.9466758}, {"type": "node", "id": 7127353033, "lat": 40.8391062, "lon": -73.9461772}, {"type": "node", "id": 7127353034, "lat": 40.8388096, "lon": -73.9457248}, {"type": "node", "id": 7127353035, "lat": 40.839112, "lon": -73.9456157}, {"type": "node", "id": 7127353036, "lat": 40.8394362, "lon": -73.9456417}, {"type": "node", "id": 7127353037, "lat": 40.8399181, "lon": -73.9455998}, {"type": "node", "id": 7127353038, "lat": 40.8407265, "lon": -73.9448237}, {"type": "node", "id": 7127353039, "lat": 40.8405357, "lon": -73.9450848}, {"type": "node", "id": 7127353040, "lat": 40.8401679, "lon": -73.9454691}, {"type": "node", "id": 7127353041, "lat": 40.8389315, "lon": -73.9462727}, {"type": "node", "id": 7127353042, "lat": 40.8362991, "lon": -73.9464025}, {"type": "node", "id": 7127353043, "lat": 40.8358629, "lon": -73.945794}, {"type": "node", "id": 7127353044, "lat": 40.8352817, "lon": -73.9454622}, {"type": "node", "id": 7127353045, "lat": 40.8356666, "lon": -73.9457847}, {"type": "node", "id": 7127353046, "lat": 40.8383925, "lon": -73.9462125}, {"type": "node", "id": 7127353047, "lat": 40.8385526, "lon": -73.9459534}, {"type": "node", "id": 7127353048, "lat": 40.838358, "lon": -73.9462857}, {"type": "node", "id": 7127353049, "lat": 40.8353274, "lon": -73.9454778}, {"type": "node", "id": 7127353051, "lat": 40.8369768, "lon": -73.9469996}, {"type": "node", "id": 7127353052, "lat": 40.8363904, "lon": -73.9467154}, {"type": "node", "id": 7127353053, "lat": 40.8360036, "lon": -73.9462535}, {"type": "node", "id": 7127353054, "lat": 40.8356339, "lon": -73.9457567}, {"type": "node", "id": 7127353055, "lat": 40.8374277, "lon": -73.9468989}, {"type": "node", "id": 7127353056, "lat": 40.8379171, "lon": -73.9468299}, {"type": "node", "id": 7127353057, "lat": 40.8383133, "lon": -73.946369}, {"type": "node", "id": 7127353058, "lat": 40.8378441, "lon": -73.947051}, {"type": "node", "id": 7127353059, "lat": 40.8384479, "lon": -73.9466241}, {"type": "node", "id": 7127353060, "lat": 40.8388319, "lon": -73.9457126}, {"type": "node", "id": 7127353061, "lat": 40.8391351, "lon": -73.9456119}, {"type": "node", "id": 7127353062, "lat": 40.8394723, "lon": -73.9456525}, {"type": "node", "id": 7127353063, "lat": 40.839942, "lon": -73.9455843}, {"type": "node", "id": 7127353064, "lat": 40.840739, "lon": -73.9448432}, {"type": "node", "id": 7127353065, "lat": 40.8404426, "lon": -73.9451825}, {"type": "node", "id": 7127353066, "lat": 40.8401008, "lon": -73.945536}, {"type": "node", "id": 7127353067, "lat": 40.8370273, "lon": -73.9468377}, {"type": "node", "id": 7127353068, "lat": 40.8362625, "lon": -73.9463601}, {"type": "node", "id": 7127353069, "lat": 40.8357889, "lon": -73.945727}, {"type": "node", "id": 7127353070, "lat": 40.8352439, "lon": -73.9454552}, {"type": "node", "id": 7127353071, "lat": 40.8360491, "lon": -73.9463276}, {"type": "node", "id": 7127353072, "lat": 40.8384047, "lon": -73.9461927}, {"type": "node", "id": 7127353073, "lat": 40.8385316, "lon": -73.9459825}, {"type": "node", "id": 7127353074, "lat": 40.8380491, "lon": -73.9467355}, {"type": "node", "id": 7127353075, "lat": 40.835229, "lon": -73.9455223}, {"type": "node", "id": 7127353077, "lat": 40.8369114, "lon": -73.9469824}, {"type": "node", "id": 7127353078, "lat": 40.8363601, "lon": -73.9466887}, {"type": "node", "id": 7127353079, "lat": 40.8359705, "lon": -73.9461934}, {"type": "node", "id": 7127353080, "lat": 40.8355951, "lon": -73.9457273}, {"type": "node", "id": 7127353081, "lat": 40.8374617, "lon": -73.9469036}, {"type": "node", "id": 7127353082, "lat": 40.8379565, "lon": -73.9468068}, {"type": "node", "id": 7127353083, "lat": 40.837094, "lon": -73.9470214}, {"type": "node", "id": 7127353084, "lat": 40.8379034, "lon": -73.9470287}, {"type": "node", "id": 7127353085, "lat": 40.8384895, "lon": -73.9465902}, {"type": "node", "id": 7127353086, "lat": 40.838615, "lon": -73.9458844}, {"type": "node", "id": 7127353087, "lat": 40.838868, "lon": -73.9456958}, {"type": "node", "id": 7127353088, "lat": 40.8391731, "lon": -73.9456085}, {"type": "node", "id": 7127353089, "lat": 40.8395054, "lon": -73.9456614}, {"type": "node", "id": 7127353090, "lat": 40.8401001, "lon": -73.9454407}, {"type": "node", "id": 7127353091, "lat": 40.8407426, "lon": -73.94485}, {"type": "node", "id": 7127353092, "lat": 40.8403588, "lon": -73.9452687}, {"type": "node", "id": 7127353093, "lat": 40.8400193, "lon": -73.9456139}, {"type": "node", "id": 7127353094, "lat": 40.836935, "lon": -73.9468173}, {"type": "node", "id": 7127353095, "lat": 40.8362238, "lon": -73.9463121}, {"type": "node", "id": 7127353096, "lat": 40.8357275, "lon": -73.9456777}, {"type": "node", "id": 7127353097, "lat": 40.8352385, "lon": -73.9454572}, {"type": "node", "id": 7127353098, "lat": 40.8365159, "lon": -73.9468101}, {"type": "node", "id": 7127353099, "lat": 40.8384192, "lon": -73.9461674}, {"type": "node", "id": 7127353100, "lat": 40.8384962, "lon": -73.946038}, {"type": "node", "id": 7127353101, "lat": 40.8377846, "lon": -73.9468923}, {"type": "node", "id": 7127353102, "lat": 40.8352333, "lon": -73.9455295}, {"type": "node", "id": 7127353104, "lat": 40.8368457, "lon": -73.946964}, {"type": "node", "id": 7127353105, "lat": 40.836314, "lon": -73.9466481}, {"type": "node", "id": 7127353106, "lat": 40.8359432, "lon": -73.9461438}, {"type": "node", "id": 7127353107, "lat": 40.8355668, "lon": -73.945705}, {"type": "node", "id": 7127353108, "lat": 40.8375042, "lon": -73.9469143}, {"type": "node", "id": 7127353109, "lat": 40.837997, "lon": -73.9467807}, {"type": "node", "id": 7127353110, "lat": 40.8371784, "lon": -73.9470339}, {"type": "node", "id": 7127353111, "lat": 40.8379534, "lon": -73.9470021}, {"type": "node", "id": 7127353112, "lat": 40.8385955, "lon": -73.9465011}, {"type": "node", "id": 7127353113, "lat": 40.8386418, "lon": -73.9458584}, {"type": "node", "id": 7127353114, "lat": 40.8388998, "lon": -73.9456819}, {"type": "node", "id": 7127353115, "lat": 40.8392387, "lon": -73.9456055}, {"type": "node", "id": 7127353116, "lat": 40.8395321, "lon": -73.9456683}, {"type": "node", "id": 7127353117, "lat": 40.8402302, "lon": -73.9453073}, {"type": "node", "id": 7127353118, "lat": 40.8407162, "lon": -73.9449025}, {"type": "node", "id": 7127353119, "lat": 40.8402608, "lon": -73.9453691}, {"type": "node", "id": 7127353120, "lat": 40.8398302, "lon": -73.9457775}, {"type": "node", "id": 7127353121, "lat": 40.8367729, "lon": -73.9467641}, {"type": "node", "id": 7127353122, "lat": 40.83616, "lon": -73.9462216}, {"type": "node", "id": 7127353123, "lat": 40.8356672, "lon": -73.9456329}, {"type": "node", "id": 7127353124, "lat": 40.8352334, "lon": -73.9454617}, {"type": "node", "id": 7127353125, "lat": 40.8368034, "lon": -73.9469495}, {"type": "node", "id": 7127353126, "lat": 40.838442, "lon": -73.9461296}, {"type": "node", "id": 7127353127, "lat": 40.8391182, "lon": -73.9461701}, {"type": "node", "id": 7127353128, "lat": 40.8375811, "lon": -73.9469246}, {"type": "node", "id": 7127353129, "lat": 40.8385975, "lon": -73.945902}, {"type": "node", "id": 7127353131, "lat": 40.8367537, "lon": -73.9469308}, {"type": "node", "id": 7127353132, "lat": 40.8362181, "lon": -73.9465491}, {"type": "node", "id": 7127353133, "lat": 40.835914, "lon": -73.946098}, {"type": "node", "id": 7127353134, "lat": 40.8355251, "lon": -73.9456814}, {"type": "node", "id": 7127353135, "lat": 40.8375478, "lon": -73.9469206}, {"type": "node", "id": 7127353136, "lat": 40.8380797, "lon": -73.9467086}, {"type": "node", "id": 7127353137, "lat": 40.8373412, "lon": -73.9470591}, {"type": "node", "id": 7127353138, "lat": 40.8379908, "lon": -73.9469806}, {"type": "node", "id": 7127353139, "lat": 40.838714, "lon": -73.9464162}, {"type": "node", "id": 7127353140, "lat": 40.8386643, "lon": -73.9458356}, {"type": "node", "id": 7127353141, "lat": 40.8389332, "lon": -73.945667}, {"type": "node", "id": 7127353142, "lat": 40.8392519, "lon": -73.9456063}, {"type": "node", "id": 7127353143, "lat": 40.8395837, "lon": -73.9456771}, {"type": "node", "id": 7127353144, "lat": 40.8403437, "lon": -73.9451911}, {"type": "node", "id": 7127353145, "lat": 40.8407428, "lon": -73.9448569}, {"type": "node", "id": 7127353146, "lat": 40.8399371, "lon": -73.9456888}, {"type": "node", "id": 7127353147, "lat": 40.8397854, "lon": -73.9458106}, {"type": "node", "id": 7127353148, "lat": 40.836685, "lon": -73.9467232}, {"type": "node", "id": 7127353149, "lat": 40.8361075, "lon": -73.9461391}, {"type": "node", "id": 7127353150, "lat": 40.8356075, "lon": -73.9455921}, {"type": "node", "id": 7127353151, "lat": 40.8352288, "lon": -73.945468}, {"type": "node", "id": 7127353152, "lat": 40.8372664, "lon": -73.9470471}, {"type": "node", "id": 7127353153, "lat": 40.8384735, "lon": -73.9460756}, {"type": "node", "id": 7127353154, "lat": 40.8391312, "lon": -73.9461633}, {"type": "node", "id": 7127353155, "lat": 40.8373396, "lon": -73.9468837}, {"type": "node", "id": 7127353156, "lat": 40.8392215, "lon": -73.9456055}, {"type": "node", "id": 7127353158, "lat": 40.8367078, "lon": -73.9469132}, {"type": "node", "id": 7127353159, "lat": 40.8361824, "lon": -73.9465079}, {"type": "node", "id": 7127353160, "lat": 40.8358809, "lon": -73.9460473}, {"type": "node", "id": 7127353161, "lat": 40.8354843, "lon": -73.9456593}, {"type": "node", "id": 7127353162, "lat": 40.8376161, "lon": -73.9469262}, {"type": "node", "id": 7127353163, "lat": 40.8381076, "lon": -73.9466756}, {"type": "node", "id": 7127353164, "lat": 40.837423, "lon": -73.9470723}, {"type": "node", "id": 7127353165, "lat": 40.8380269, "lon": -73.9469569}, {"type": "node", "id": 7127353166, "lat": 40.8386866, "lon": -73.9458155}, {"type": "node", "id": 7127353167, "lat": 40.8389662, "lon": -73.9456534}, {"type": "node", "id": 7127353168, "lat": 40.8392785, "lon": -73.9456096}, {"type": "node", "id": 7127353169, "lat": 40.8396324, "lon": -73.9456806}, {"type": "node", "id": 7127353170, "lat": 40.8404018, "lon": -73.9451334}, {"type": "node", "id": 7127353171, "lat": 40.8407421, "lon": -73.9448649}, {"type": "node", "id": 7127353172, "lat": 40.8396203, "lon": -73.9459305}, {"type": "node", "id": 7127353173, "lat": 40.8396852, "lon": -73.9458834}, {"type": "node", "id": 7127353174, "lat": 40.8366111, "lon": -73.9466801}, {"type": "node", "id": 7127353175, "lat": 40.8360701, "lon": -73.9460778}, {"type": "node", "id": 7198971061, "lat": 40.8339724, "lon": -73.9452646}, {"type": "node", "id": 8725182290, "lat": 40.8387985, "lon": -73.9457322}, {"type": "node", "id": 13030298571, "lat": 40.8355593, "lon": -73.9441484, "tags": {"addr:city": "New York", "addr:housenumber": "3821", "addr:state": "NY", "addr:street": "Broadway", "amenity": "restaurant", "cuisine": "burger", "name": "Hilltop", "outdoor_seating": "yes", "toilets": "yes"}}, {"type": "node", "id": 13038607905, "lat": 40.8399277, "lon": -73.9455935}, {"type": "node", "id": 13243810169, "lat": 40.8343803, "lon": -73.9439731, "tags": {"addr:city": "New York", "addr:housenumber": "554", "addr:postcode": "10032", "addr:state": "NY", "addr:street": "W 158th", "amenity": "cafe", "internet_access": "yes", "internet_access:fee": "no", "name": "Five Flies", "opening_hours": "Mo-Su 07:00-18:00", "website": "https://www.fivefliescoffee.com/"}}, {"type": "way", "id": 357523569, "nodes": [4763738146, 7198971061, 3627501381, 4763738145, 4763738146], "tags": {"leisure": "park", "name": "Ilka Tanya Pay\u00e1n Park", "name:etymology:wikidata": "Q5998496", "operator": "New York City Department of Parks and Recreation", "operator:short": "NYC Parks", "operator:type": "government", "operator:wikidata": "Q1894232", "website": "https://www.nycgovparks.org/parks/ilka-tanya-payan-park"}}, {"type": "way", "id": 476650290, "nodes": [7127353143, 7127353116, 7127353089, 7127353062, 7127353036, 7127353010, 7127352985, 7127352959, 7127352932, 7127353168, 7127353142, 7127353115, 7127353156, 7127353088, 7127353061, 7127353035, 7127353009, 7127352984, 7127352958, 7127352931, 7127353167, 7127353141, 7127353114, 7127353087, 7127353060, 7127353034, 8725182290, 7127353008, 7127352983, 7127352957, 7127352930, 7127353166, 7127353140, 7127353113, 7127353086, 7127353129, 7127352996, 7127353021, 7127353047, 7127353073, 7127353100, 7127352982, 7127353153, 7127352917, 7127353126, 7127353099, 7127353072, 7127353046, 7127353020, 7127353048, 7127353057, 7127353030, 7127353005, 7127352979, 7127352953, 7127352927, 7127353163, 7127353136, 7127353074, 7127353109, 7127353082, 7127353056, 7127353029, 7127353004, 7127353101, 7127352978, 7127352952, 7127352926, 7127353162, 7127353128, 7127353135, 7127353108, 7127353081, 7127353055, 7127353028, 7127353155, 7127353003, 7127353067, 7127353094, 7127352919, 7127353121, 7127353148, 7127353174, 7127352938, 7127352965, 7127352945, 7127352991, 7127353016, 7127353042, 7127353068, 7127353095, 7127352972, 7127353122, 7127353149, 7127353175, 7127352939, 7127352966, 7127352992, 7127353017, 7127353043, 7127352998, 7127353069, 7127353096, 7127353123, 7127353150, 7127352914, 7127352940, 7127353023, 7127353049, 7127353044, 7127353018, 7127352993, 7127352967, 7127353070, 7127353097, 7127353124, 7127353151, 7127352915, 7127352941, 7127352968, 7127352994, 7127353019, 7127353075, 7127353102, 7127352977, 7127352951, 7127352925, 7127353161, 7127353134, 7127353107, 7127353080, 7127353054, 7127353045, 7127353027, 7127353002, 7127352976, 7127352950, 7127352924, 7127353160, 7127353133, 7127353106, 7127353079, 7127353053, 7127353026, 7127353071, 7127353001, 7127352975, 7127352949, 7127352923, 7127353159, 7127353132, 7127353105, 7127353078, 7127353052, 7127353025, 7127353000, 7127353098, 7127352974, 7127352948, 7127352922, 7127353158, 7127353131, 7127353125, 7127353104, 7127353077, 7127353051, 7127353083, 7127353110, 7127353152, 7127353137, 7127353164, 7127352928, 7127352954, 7127352980, 7127353006, 7127353031, 7127352916, 7127353058, 7127353084, 7127353111, 7127353138, 7127353165, 7127352929, 7127352955, 7127352942, 7127352981, 7127353007, 7127353032, 7127353059, 7127353085, 7127353112, 7127353139, 7127352969, 7127352995, 7127353041, 7127352970, 7127352943, 7127352956, 7127353033, 7127353127, 7127353154, 7127352918, 7127352944, 7127352971, 7127353015, 7127352936, 7127352990, 7127352964, 7127352937, 7127352997, 7127353172, 7127353173, 7127353147, 7127353120, 7127353022, 7127353146, 7127353093, 7127353066, 7127353040, 7127353119, 7127353092, 7127353065, 7127353039, 7127353013, 7127353118, 4701483771, 7127352988, 7127352962, 7127352935, 7127353171, 7127353145, 7127353091, 7127353064, 7127353038, 7127353012, 7127352987, 7127352999, 7127352961, 7127352934, 7127353170, 7127353144, 7127353117, 7127352973, 7127353090, 7127353014, 7127352989, 7127352963, 7127353063, 13038607905, 7127353037, 7127353011, 7127352946, 7127352986, 7127352960, 7127352933, 7127352920, 7127353169, 7127353143], "tags": {"leisure": "park"}}]}