{"version": 0.6, "generator": "Overpass API 0.7.62.8 e802775f", "osm3s": {"timestamp_osm_base": "2025-12-01T16:29:00Z", "copyright": "The data included in this document is from www.openstreetmap.org. The data is made available under ODbL."}, "elements": [{"type": "node", "id": 357544577, "lat": 40.7012239, "lon": -73.9445117, "tags": {"amenity": "school", "ele": "5", "gnis:feature_id": "942331", "name": "All Saints High School"}}, {"type": "node", "id": 357619272, "lat": 40.7011228, "lon": -73.9445018, "tags": {"amenity": "school", "ele": "5", "gnis:feature_id": "2081877", "name": "All Saints Elementary School"}}, {"type": "node", "id": 357637266, "lat": 40.7011922, "lon": -73.9385073, "tags": {"ele": "12", "gnis:feature_id": "2377133", "leisure": "park", "name": "Garden Playground", "wikidata": "Q49492810"}}, {"type": "node", "id": 1927720909, "lat": 40.7006444, "lon": -73.9438427, "tags": {"amenity": "restaurant", "cuisine": "mexican", "name": "Cactus Mexican Restaurant"}}, {"type": "node", "id": 2269706631, "lat": 40.6978659, "lon": -73.9384574}, {"type": "node", "id": 2269706632, "lat": 40.6978854, "lon": -73.9382684}, {"type": "node", "id": 2269706633, "lat": 40.6976606, "lon": -73.9382125}, {"type": "node", "id": 2269706634, "lat": 40.6976411, "lon": -73.9384102}, {"type": "node", "id": 2838402264, "lat": 40.7024847, "lon": -73.9418038}, {"type": "node", "id": 2838402277, "lat": 40.7025574, "lon": -73.9418158}, {"type": "node", "id": 2838402526, "lat": 40.7029814, "lon": -73.9418861}, {"type": "node", "id": 2838402530, "lat": 40.7030269, "lon": -73.9418936}, {"type": "node", "id": 4259440712, "lat": 40.7005904, "lon": -73.9440052, "tags": {"addr:city": "Brooklyn", "addr:housenumber": "715", "addr:postcode": "11206", "addr:state": "NY", "addr:street": "Flushing Avenue", "amenity": "restaurant", "cuisine": "mexican", "name": "Habanero Cafe Mexican", "takeaway": "yes"}}, {"type": "node", "id": 5509332413, "lat": 40.6984541, "lon": -73.9380789}, {"type": "node", "id": 5509332414, "lat": 40.698361, "lon": -73.9379453}, {"type": "node", "id": 5509332415, "lat": 40.6982879, "lon": -73.9380104}, {"type": "node", "id": 6770679586, "lat": 40.7025176, "lon": -73.941109}, {"type": "node", "id": 6770679590, "lat": 40.7022586, "lon": -73.9410661}, {"type": "node", "id": 6952884368, "lat": 40.7000569, "lon": -73.9411085, "tags": {"addr:city": "Brooklyn", "addr:housenumber": "774", "addr:postcode": "11206", "addr:state": "NY", "addr:street": "Broadway", "amenity": "cafe", "branch": "774 Broadway", "brand": "Starbucks", "brand:wikidata": "Q37158", "cuisine": "coffee_shop", "indoor_seating": "yes", "internet_access": "yes", "name": "Starbucks", "official_name": "Starbucks Coffee", "outdoor_seating": "no", "phone": "+1 917-246-0280", "ref": "1021445", "takeaway": "yes", "website": "https://www.starbucks.com/store-locator/store/1021445/774-broadway-774-broadway-brooklyn-ny-112065316-us"}}, {"type": "node", "id": 9374700176, "lat": 40.7025153, "lon": -73.9414826}, {"type": "node", "id": 9374700177, "lat": 40.7024826, "lon": -73.9414772}, {"type": "node", "id": 9374700178, "lat": 40.7022865, "lon": -73.9407723}, {"type": "node", "id": 9374700179, "lat": 40.7031205, "lon": -73.9409105}, {"type": "node", "id": 9374700198, "lat": 40.7002211, "lon": -73.9374361}, {"type": "node", "id": 9374700199, "lat": 40.7004456, "lon": -73.9372184}, {"type": "node", "id": 9374700200, "lat": 40.7004184, "lon": -73.9371696}, {"type": "node", "id": 9374700201, "lat": 40.7006326, "lon": -73.9369618}, {"type": "node", "id": 9374700202, "lat": 40.7013002, "lon": -73.9381599}, {"type": "node", "id": 9374700203, "lat": 40.7008615, "lon": -73.9385852}, {"type": "node", "id": 10067180313, "lat": 40.7013535, "lon": -73.942403, "tags": {"addr:city": "Brooklyn", "addr:housenumber": "9", "addr:postcode": "11206", "addr:state": "NY", "addr:street": "Graham Ave", "amenity": "college", "check_date": "2025-05-12", "internet_access": "yes", "internet_access:fee": "students", "name": "Boricua College", "phone": "+1-718-963-4112", "website": "https://www.boricuacollege.edu/"}}, {"type": "node", "id": 10067180314, "lat": 40.7014386, "lon": -73.9424037, "tags": {"addr:city": "Brooklyn", "addr:housenumber": "11", "addr:postcode": "11206", "addr:state": "NY", "addr:street": "Graham Avenue", "amenity": "restaurant", "cuisine": "spanish;latin_american", "name": "George's Latin American Bistro"}}, {"type": "node", "id": 11023996243, "lat": 40.7010213, "lon": -73.9412824, "tags": {"addr:city": "Brooklyn", "addr:housenumber": "785", "addr:postcode": "11206", "addr:state": "NY", "addr:street": "Flushing Avenue", "air_conditioning": "yes", "amenity": "restaurant", "brand": "IHOP", "brand:wikidata": "Q1185675", "cuisine": "breakfast;pancake", "delivery": "yes", "internet_access": "wlan", "internet_access:fee": "no", "name": "IHOP", "opening_hours": "07:00-22:00; Fr,Sa 07:00-00:00", "phone": "+1-718-408-1368", "takeaway": "yes", "toilets": "yes", "toilets:access": "customers", "website": "https://restaurants.ihop.com/en-us/ny/brooklyn/breakfast-785-flushing-ave-3353"}}, {"type": "node", "id": 11575046645, "lat": 40.7007353, "lon": -73.942733, "tags": {"name": "Talisman & DeLorenz, PC", "office": "lawyer", "phone": "+1-718-302-6802"}}, {"type": "node", "id": 13112903048, "lat": 40.701104, "lon": -73.9383501}, {"type": "way", "id": 217658306, "nodes": [2269706631, 2269706632, 2269706633, 2269706634, 2269706631], "tags": {"leisure": "park"}}, {"type": "way", "id": 573724120, "nodes": [5509332413, 5509332414, 5509332415, 5509332413], "tags": {"leisure": "park"}}, {"type": "way", "id": 1016411986, "nodes": [2838402530, 2838402526, 2838402277, 2838402264, 9374700176, 9374700177, 6770679586, 6770679590, 9374700178, 9374700179, 2838402530], "tags": {"amenity": "school", "name": "Public School 257"}}, {"type": "way", "id": 1016411992, "nodes": [9374700198, 9374700199, 9374700200, 9374700201, 9374700202, 13112903048, 9374700203, 9374700198], "tags": {"amenity": "school", "name": "Public School 120", "wikidata": "Q117819894"}}]}